{
  "$schema": "http://json-schema.org/draft-07/schema#",
  "title": "QueryMsg",
  "oneOf": [
    {
      "type": "object",
      "required": [
        "participants_count"
      ],
      "properties": {
        "participants_count": {
          "type": "object"
        }
      },
      "additionalProperties": false
    },
    {
      "type": "object",
      "required": [
        "get_sale_status"
      ],
      "properties": {
        "get_sale_status": {
          "type": "object"
        }
      },
      "additionalProperties": false
    },
    {
      "type": "object",
      "required": [
        "get_participants"
      ],
      "properties": {
        "get_participants": {
          "type": "object",
          "required": [
            "limit",
            "page"
          ],
          "properties": {
            "limit": {
              "type": "integer",
              "format": "uint64",
              "minimum": 0.0
            },
            "page": {
              "type": "integer",
              "format": "uint64",
              "minimum": 0.0
            }
          }
        }
      },
      "additionalProperties": false
    },
    {
      "type": "object",
      "required": [
        "get_participant"
      ],
      "properties": {
        "get_participant": {
          "type": "object",
          "required": [
            "user"
          ],
          "properties": {
            "user": {
              "type": "string"
            }
          }
        }
      },
      "additionalProperties": false
    },
    {
      "type": "object",
      "required": [
        "presale_info"
      ],
      "properties": {
        "presale_info": {
          "type": "object"
        }
      },
      "additionalProperties": false
    }
  ]
}
